awsparameters/__init__.py
awsparameters/_version.py
awsparameters/manager.py
aws_parameters-0.1.8.dist-info/LICENSE
aws_parameters-0.1.8.dist-info/METADATA
aws_parameters-0.1.8.dist-info/WHEEL
aws_parameters-0.1.8.dist-info/top_level.txt
aws_parameters-0.1.8.dist-info/RECORD
