Metadata-Version: 2.1
Name: aws-parameters
Version: 0.1.8
Summary: Streamlined, efficient access to configuration values in AWS SSM Parameter Store and SecretsManager.
Author-email: "@chrisammon3000" <gclindsey@gmail.com>
License: MIT License
Keywords: aws,systems manager,configuration,secretsmanager
Classifier: Development Status :: 3 - Alpha
Classifier: License :: OSI Approved :: MIT License
Classifier: Operating System :: OS Independent
Classifier: Programming Language :: Python :: 3.10
Classifier: Topic :: Software Development :: Libraries :: Python Modules
Classifier: Topic :: Utilities
Requires-Python: >=3.8
License-File: LICENSE
Requires-Dist: boto3 >=1.15.3
Requires-Dist: boto3-stubs-lite[secretsmanager,ssm] >=1.15.3
Provides-Extra: dev
Requires-Dist: black >=21.12 ; extra == 'dev'
Requires-Dist: pre-commit >=2.20.0 ; extra == 'dev'
Requires-Dist: mypy >=1.4.1 ; extra == 'dev'
Requires-Dist: boto3-stubs[secretsmanager,ssm] >=1.15.3 ; extra == 'dev'
Provides-Extra: test
Requires-Dist: pytest >=7.2.0 ; extra == 'test'
Requires-Dist: pytest-cov >=4.0 ; extra == 'test'
Requires-Dist: coverage >=6.0 ; extra == 'test'
Requires-Dist: boto3 >=1.20 ; extra == 'test'
Requires-Dist: moto[secretsmanager,ssm] >=2.2 ; extra == 'test'
Requires-Dist: tox >=4.6.4 ; extra == 'test'
